MANIFEST.in
requirements.txt
setup.py
rqalpha_mod_vnpy/VERSION.txt
rqalpha_mod_vnpy/__init__.py
rqalpha_mod_vnpy/__init__.pyc
rqalpha_mod_vnpy/ctp_gateway.pyc
rqalpha_mod_vnpy/data_factory.pyc
rqalpha_mod_vnpy/mod.py
rqalpha_mod_vnpy/mod.pyc
rqalpha_mod_vnpy/utils.py
rqalpha_mod_vnpy/utils.pyc
rqalpha_mod_vnpy/vnpy_broker.py
rqalpha_mod_vnpy/vnpy_broker.pyc
rqalpha_mod_vnpy/vnpy_data_source.py
rqalpha_mod_vnpy/vnpy_data_source.pyc
rqalpha_mod_vnpy/vnpy_engine.pyc
rqalpha_mod_vnpy/vnpy_event_source.py
rqalpha_mod_vnpy/vnpy_event_source.pyc
rqalpha_mod_vnpy/vnpy_gateway.pyc
rqalpha_mod_vnpy/vnpy_price_board.py
rqalpha_mod_vnpy/vnpy_price_board.pyc
rqalpha_mod_vnpy.egg-info/PKG-INFO
rqalpha_mod_vnpy.egg-info/SOURCES.txt
rqalpha_mod_vnpy.egg-info/dependency_links.txt
rqalpha_mod_vnpy.egg-info/not-zip-safe
rqalpha_mod_vnpy.egg-info/requires.txt
rqalpha_mod_vnpy.egg-info/top_level.txt
rqalpha_mod_vnpy/ctp/__init__.py
rqalpha_mod_vnpy/ctp/__init__.pyc
rqalpha_mod_vnpy/ctp/api.py
rqalpha_mod_vnpy/ctp/api.pyc
rqalpha_mod_vnpy/ctp/data_cache.py
rqalpha_mod_vnpy/ctp/data_cache.pyc
rqalpha_mod_vnpy/ctp/data_dict.py
rqalpha_mod_vnpy/ctp/data_dict.pyc
rqalpha_mod_vnpy/ctp/gateway.py
rqalpha_mod_vnpy/ctp/gateway.pyc
rqalpha_mod_vnpy/vnpy/__init__.py
rqalpha_mod_vnpy/vnpy/__init__.pyc