Metadata-Version: 1.1
Name: rqalpha-mod-vnpy
Version: 0.9.30
Summary: A mod for RQAlpha to connect with VN.PY
Home-page: https://github.com/ricequant/rqalpha-mod-vnpy
Author: ricequant
Author-email: public@ricequant.com
License: Apache License v2
Platform: UNKNOWN
Classifier: Programming Language :: Python
Classifier: Operating System :: Microsoft :: Windows
Classifier: Operating System :: Unix
Classifier: Programming Language :: Python :: 2.7
